litefeel/__init__.py
litefeel/pycommon/__init__.py
litefeel/pycommon/color.py
litefeel/pycommon/command.py
litefeel/pycommon/data.py
litefeel/pycommon/ftp.py
litefeel/pycommon/hash.py
litefeel/pycommon/io.py
litefeel/pycommon/math.py
litefeel/pycommon/misc.py
litefeel_pycommon-0.4.17.dist-info/METADATA
litefeel_pycommon-0.4.17.dist-info/WHEEL
litefeel_pycommon-0.4.17.dist-info/licenses/LICENSE
litefeel_pycommon-0.4.17.dist-info/RECORD
