Metadata-Version: 2.4
Name: litefeel-pycommon
Version: 0.4.17
Summary: my python common lib
Project-URL: Homepage, http://github.com/litefeel/pycommon
Project-URL: Repository, http://github.com/litefeel/pycommon.git
Project-URL: Bug Tracker, http://github.com/litefeel/pycommon/issues
Author-email: litefeel <litefeel@gmail.com>
License: MIT License
License-File: LICENSE
Keywords: lib
Classifier: Development Status :: 4 - Beta
Classifier: Programming Language :: Python
Classifier: Topic :: Software Development :: Libraries :: Python Modules
Requires-Python: >=3.10
Requires-Dist: openpyxl
